{
    "9537206522": {
        "sports_id": "1",
        "selected_game": {
            "MatchUID": "65175",
            "tournament_name": "Big Bash League",
            "max_prize": "50000.00",
            "ScheduleDate": "2023-12-20 08:15:00",
            "ScheduleDateOriginal": "2023-12-20 08:15:00",
            "GameGroupID": "create_12813"
        }
    },
    "1234567890": {
        "sports_id": "1",
        "selected_game": {
            "MatchUID": "65840",
            "tournament_name": "Bangladesh tour of New Zealand",
            "max_prize": "50000.00",
            "ScheduleDate": "2023-12-19 22:00:00",
            "ScheduleDateOriginal": "2023-12-19 22:00:00"
        }
    },
    "9427712949": {
        "sports_id": "1",
        "selected_game": {
            "MatchUID": "63148",
            "tournament_name": "England tour of West Indies",
            "max_prize": "50000.00",
            "ScheduleDate": "2023-12-19 20:00:00",
            "ScheduleDateOriginal": "2023-12-19 20:00:00"
        }
    }
}